<?xml version="1.0" encoding="UTF-8" standalone="no"?><PrestamosDOM><prestamo><id>1</id><fecha>15/10/2022</fecha><libro>El principito</libro><cliente>cliente</cliente></prestamo><prestamo><id>2</id><fecha>10/10/2022</fecha><libro>La celestina</libro><cliente>MariaPerez</cliente></prestamo><prestamo><id>3</id><fecha>20/10/2022</fecha><libro>Orgullo y prejuicio</libro><cliente>PepeGarcia</cliente></prestamo><prestamo><id>4</id><fecha>21/10/2022</fecha><libro>1 El principito</libro><cliente>1 Cliente Cliente</cliente></prestamo><prestamo><id>5</id><fecha>20/10/2022</fecha><libro>4 La casa de Bernarda Alba</libro><cliente>3 Maria Perez</cliente></prestamo></PrestamosDOM>